mkdocs_material_extras/__init__.py
mkdocs_material_extras/theme/assets/javascripts/mathjax.js
mkdocs_material_extras/theme/assets/stylesheets/extra.9add2662.min.css
mkdocs_material_extras-0.0.11.dist-info/LICENSE
mkdocs_material_extras-0.0.11.dist-info/METADATA
mkdocs_material_extras-0.0.11.dist-info/WHEEL
mkdocs_material_extras-0.0.11.dist-info/entry_points.txt
mkdocs_material_extras-0.0.11.dist-info/top_level.txt
mkdocs_material_extras-0.0.11.dist-info/RECORD
