Metadata-Version: 2.1
Name: mkdocs-material-extras
Version: 0.0.11
Summary: mkdocs material extras
Home-page: https://github.com/Dup4/mkdocs-material-extras#readme
Author: Dup4
Author-email: lyuzhi.pan@gmail.com
License: MIT
Keywords: mkdocs,material,theme
Classifier: Development Status :: 5 - Production/Stable
Classifier: Environment :: Console
Classifier: Intended Audience :: Developers
Classifier: License :: OSI Approved :: MIT License
Classifier: Operating System :: OS Independent
Classifier: Programming Language :: Python :: 3
Classifier: Programming Language :: Python :: 3.7
Classifier: Programming Language :: Python :: 3.8
Classifier: Programming Language :: Python :: 3.9
Classifier: Programming Language :: Python :: 3.10
Classifier: Topic :: Internet :: WWW/HTTP :: Dynamic Content
Classifier: Topic :: Software Development :: Libraries :: Python Modules
Classifier: Topic :: Text Processing :: Filters
Classifier: Topic :: Text Processing :: Markup :: HTML
Requires-Python: >=3.7
License-File: LICENSE
Requires-Dist: mkdocs-material (==8.2.16)
